printguard/__init__.py
printguard/app.py
printguard/models.py
printguard/model/best_model.pt
printguard/model/opt.json
printguard/model/prototypes/cache/prototypes_0f91fd025b3131ac9ec2dda557e655f9.pkl
printguard/protonets/__init__.py
printguard/protonets/engine.py
printguard/protonets/data/__init__.py
printguard/protonets/data/base.py
printguard/protonets/data/fault.py
printguard/protonets/models/__init__.py
printguard/protonets/models/factory.py
printguard/protonets/models/few_shot.py
printguard/protonets/models/utils.py
printguard/protonets/utils/__init__.py
printguard/protonets/utils/data.py
printguard/protonets/utils/log.py
printguard/protonets/utils/model.py
printguard/routes/__init__.py
printguard/routes/alert_routes.py
printguard/routes/camera_routes.py
printguard/routes/detection_routes.py
printguard/routes/index_routes.py
printguard/routes/notification_routes.py
printguard/routes/printer_routes.py
printguard/routes/setup_routes.py
printguard/routes/sse_routes.py
printguard/static/css/cloudflare_setup.css
printguard/static/css/index.css
printguard/static/css/setup.css
printguard/static/css/universal.css
printguard/static/fonts/Big Money-ne.flf
printguard/static/js/cloudflare_setup.js
printguard/static/js/index.js
printguard/static/js/notifications.js
printguard/static/js/setup.js
printguard/static/js/sse.js
printguard/static/js/sw.js
printguard/static/js/utils.js
printguard/templates/cloudflare_setup.html
printguard/templates/index.html
printguard/templates/setup.html
printguard/utils/__init__.py
printguard/utils/alert_utils.py
printguard/utils/camera_state_manager.py
printguard/utils/camera_utils.py
printguard/utils/cloudflare_utils.py
printguard/utils/config.py
printguard/utils/detection_utils.py
printguard/utils/inference_lib.py
printguard/utils/model_utils.py
printguard/utils/notification_utils.py
printguard/utils/printer_utils.py
printguard/utils/setup_utils.py
printguard/utils/sse_utils.py
printguard/utils/stream_utils.py
printguard-1.0.0b2.dist-info/METADATA
printguard-1.0.0b2.dist-info/WHEEL
printguard-1.0.0b2.dist-info/entry_points.txt
printguard-1.0.0b2.dist-info/top_level.txt
printguard-1.0.0b2.dist-info/RECORD
