Metadata-Version: 2.4
Name: printguard
Version: 1.0.0b2
Summary: PrintGuard - Real-time Defect Detection on Edge-devices
Author-email: Oliver Bravery <dev@oliverbravery.uk>
Requires-Python: >=3.13
Requires-Dist: fastapi
Requires-Dist: uvicorn[standard]
Requires-Dist: pywebpush
Requires-Dist: apscheduler
Requires-Dist: python-dotenv
Requires-Dist: torch
Requires-Dist: torchvision
Requires-Dist: pillow
Requires-Dist: opencv-python-headless
Requires-Dist: python-multipart
Requires-Dist: keyring
Requires-Dist: trustme
Requires-Dist: platformdirs
Requires-Dist: sse-starlette
Requires-Dist: ngrok
Requires-Dist: cryptography
